<?xml version="1.0" encoding="UTF-8"?>
<root>

<var name="N3n" longname="Nitrate"  units="g/m3"></var>
<var name="N1p" longname="Phosphate" units="g/m3"></var>
<var name="DIC" longname="Dissolved inorganic carbon"  units="g/m3"></var>
<var name="POC" longname="Particulate Organic Carbon" units="g/m3"></var>
<var name="DOC" longname="Dissolved Organic Carbon" units="g/m3"></var>
<var name="ALK" longname="Alkalinity" units="Gmol/km3"></var>

<RIVERS >

<river name="Po" salinity="18.0" > 
<concentrations>
<var name="N3n" value="1.739964749" ></var>
<var name="N1p" value="0.05973986885" ></var>
<var name="DIC" value="36.44620222" ></var>
<var name="POC" value="1.516579034" ></var>
<var name="DOC" value="2.290015211" ></var>
<var name="ALK" value="2.915344542" ></var>
</concentrations>
<Mouths>
<mouth I="512" J="358" id="4" name="Po Maistra"></mouth>
<mouth I="514" J="357" id="5" name="Po Tramontana"></mouth>
<mouth I="516" J="356" id="6" name="Po Dritta"></mouth>
<mouth I="516" J="355" id="7" name="Po Scirocco + Po Bonifazio"></mouth>
<mouth I="515" J="534" id="8" name="Po Bastimento"></mouth>
<mouth I="514" J="353" id="9" name="Po Bocca Tolle"></mouth>
<mouth I="512" J="351" id="10" name="Po Gnocca"></mouth>
<mouth I="511" J="351" id="11" name="Po Goro"></mouth>
<mouth I="511" J="359" id="12" name="Po Levante"></mouth>
<mouth I="509" J="351" id="13" name="Po Volano"></mouth>

</Mouths>
</river>


<river name="Vjose" salinity="15.0" >
<concentrations>
<var name="N3n" value="1.739964749" ></var>
<var name="N1p" value="0.05973986885" ></var>
<var name="DIC" value="36.44620222" ></var>
<var name="POC" value="1.516579034" ></var>
<var name="DOC" value="2.290015211" ></var>
<var name="ALK" value="2.915344542" ></var>
</concentrations>
<Mouths><mouth I="677" J="252" id="16" name="Vjose"></mouth></Mouths>
</river>


<river name="Seman" salinity="15.0" >
<concentrations>
<var name="N3n" value="1.739964749" ></var>
<var name="N1p" value="0.05973986885" ></var>
<var name="DIC" value="36.44620222" ></var>
<var name="POC" value="1.516579034" ></var>
<var name="DOC" value="2.290015211" ></var>
<var name="ALK" value="2.915344542" ></var>
</concentrations>
<Mouths><mouth I="679" J="256" id="17" name="Seman"></mouth></Mouths>
</river>

<river name="Buna/Bojana" salinity="15.0" >
<concentrations>
<var name="N3n" value="1.739964749" ></var>
<var name="N1p" value="0.05973986885" ></var>
<var name="DIC" value="36.44620222" ></var>
<var name="POC" value="1.516579034" ></var>
<var name="DOC" value="2.290015211" ></var>
<var name="ALK" value="2.915344542" ></var>
</concentrations>
<Mouths>
<mouth I="679" J="280" id="18" name="Boiana Sud"></mouth>
<mouth I="678" J="281" id="19" name="Boiana Nord"></mouth>
</Mouths>
</river>


<river name="Piave" salinity="15.0" >
<concentrations>
<var name="N3n" value="1.739964749" ></var>
<var name="N1p" value="0.05973986885" ></var>
<var name="DIC" value="36.44620222" ></var>
<var name="POC" value="1.516579034" ></var>
<var name="DOC" value="2.290015211" ></var>
<var name="ALK" value="2.915344542" ></var>
</concentrations>
<Mouths><mouth I="519" J="369" id="20" name="Piave"></mouth></Mouths>
</river>


<river name="Tagliamento" salinity="15.0" >
<concentrations>
<var name="N3n" value="1.739964749" ></var>
<var name="N1p" value="0.05973986885" ></var>
<var name="DIC" value="36.44620222" ></var>
<var name="POC" value="1.516579034" ></var>
<var name="DOC" value="2.290015211" ></var>
<var name="ALK" value="2.915344542" ></var>
</concentrations>
<Mouths><mouth I="529" J="372" id="21" name="Tagliamento"></mouth></Mouths>
</river>


<river name="Soca/Isonzo" salinity="15.0" >
<concentrations>
<var name="N3n" value="1.739964749" ></var>
<var name="N1p" value="0.05973986885" ></var>
<var name="DIC" value="36.44620222" ></var>
<var name="POC" value="1.516579034" ></var>
<var name="DOC" value="2.290015211" ></var>
<var name="ALK" value="2.915344542" ></var>
</concentrations>
<Mouths><mouth I="539" J="374" id="22" name="Soca/Isonzo"></mouth></Mouths>
</river>


<river name="Livenza" salinity="15.0" >
<concentrations>
<var name="N3n" value="1.739964749" ></var>
<var name="N1p" value="0.05973986885" ></var>
<var name="DIC" value="36.44620222" ></var>
<var name="POC" value="1.516579034" ></var>
<var name="DOC" value="2.290015211" ></var>
<var name="ALK" value="2.915344542" ></var>
</concentrations>
<Mouths><mouth I="523" J="370" id="23" name="Livenza"></mouth></Mouths>
</river>


<river name="Brenta-Baccaglione" salinity="15.0" >
<concentrations>
<var name="N3n" value="1.739964749" ></var>
<var name="N1p" value="0.05973986885" ></var>
<var name="DIC" value="36.44620222" ></var>
<var name="POC" value="1.516579034" ></var>
<var name="DOC" value="2.290015211" ></var>
<var name="ALK" value="2.915344542" ></var>
</concentrations>
<Mouths><mouth I="510" J="361" id="24" name="Brenta-Baccaglione"></mouth></Mouths>
</river>

<river name="Adige" salinity="15.0" >
<concentrations>
<var name="N3n" value="1.739964749" ></var>
<var name="N1p" value="0.05973986885" ></var>
<var name="DIC" value="36.44620222" ></var>
<var name="POC" value="1.516579034" ></var>
<var name="DOC" value="2.290015211" ></var>
<var name="ALK" value="2.915344542" ></var>
</concentrations>
<Mouths><mouth I="511" J="360" id="25" name="Adige"></mouth></Mouths>
</river>


<river name="Lika" salinity="15.0" >
<concentrations>
<var name="N3n" value="1.739964749" ></var>
<var name="N1p" value="0.05973986885" ></var>
<var name="DIC" value="36.44620222" ></var>
<var name="POC" value="1.516579034" ></var>
<var name="DOC" value="2.290015211" ></var>
<var name="ALK" value="2.915344542" ></var>
</concentrations>
<Mouths><mouth I="569" J="347" id="26" name="Lika"></mouth></Mouths>
</river>

<river name="Reno" salinity="15.0" >
<concentrations>
<var name="N3n" value="1.739964749" ></var>
<var name="N1p" value="0.05973986885" ></var>
<var name="DIC" value="36.44620222" ></var>
<var name="POC" value="1.516579034" ></var>
<var name="DOC" value="2.290015211" ></var>
<var name="ALK" value="2.915344542" ></var>
</concentrations>
<Mouths><mouth I="509" J="347" id="27" name="Reno"></mouth></Mouths>
</river>


<river name="Krka" salinity="15.0" >
<concentrations>
<var name="N3n" value="1.739964749" ></var>
<var name="N1p" value="0.05973986885" ></var>
<var name="DIC" value="36.44620222" ></var>
<var name="POC" value="1.516579034" ></var>
<var name="DOC" value="2.290015211" ></var>
<var name="ALK" value="2.915344542" ></var>
</concentrations>
<Mouths><mouth I="594" J="324" id="28" name="Krka"></mouth></Mouths>
</river>


<river name="Neretva" salinity="15.0" >
<concentrations>
<var name="N3n" value="1.739964749" ></var>
<var name="N1p" value="0.05973986885" ></var>
<var name="DIC" value="36.44620222" ></var>
<var name="POC" value="1.516579034" ></var>
<var name="DOC" value="2.290015211" ></var>
<var name="ALK" value="2.915344542" ></var>
</concentrations>
<Mouths><mouth I="631" J="309" id="30" name="Netetva"></mouth></Mouths>
</river>

<river name="Trebisjnica" salinity="15.0" >
<concentrations>
<var name="N3n" value="1.739964749" ></var>
<var name="N1p" value="0.05973986885" ></var>
<var name="DIC" value="36.44620222" ></var>
<var name="POC" value="1.516579034" ></var>
<var name="DOC" value="2.290015211" ></var>
<var name="ALK" value="2.915344542" ></var>
</concentrations>
<Mouths><mouth I="651" J="298" id="32" name="Trebisjnica"></mouth></Mouths>
</river>

<river name="Mati" salinity="15.0" >
<concentrations>
<var name="N3n" value="1.739964749" ></var>
<var name="N1p" value="0.05973986885" ></var>
<var name="DIC" value="36.44620222" ></var>
<var name="POC" value="1.516579034" ></var>
<var name="DOC" value="2.290015211" ></var>
<var name="ALK" value="2.915344542" ></var>
</concentrations>
<Mouths><mouth I="683" J="276" id="35" name="Mati"></mouth></Mouths>
</river>

<river name="Arachtos" salinity="15.0" >
<concentrations>
<var name="N3n" value="1.739964749" ></var>
<var name="N1p" value="0.05973986885" ></var>
<var name="DIC" value="36.44620222" ></var>
<var name="POC" value="1.516579034" ></var>
<var name="DOC" value="2.290015211" ></var>
<var name="ALK" value="2.915344542" ></var>
</concentrations>
<Mouths><mouth I="710" J="213" id="41" name="Arachtos"></mouth></Mouths>
</river>

<river name="Acheloos" salinity="15.0" >
<concentrations>
<var name="N3n" value="1.739964749" ></var>
<var name="N1p" value="0.05973986885" ></var>
<var name="DIC" value="36.44620222" ></var>
<var name="POC" value="1.516579034" ></var>
<var name="DOC" value="2.290015211" ></var>
<var name="ALK" value="2.915344542" ></var>
</concentrations>
<Mouths><mouth I="720" J="197" id="43" name="Acheloos"></mouth></Mouths>
</river>


<river name="Shkumbini" salinity="15.0" >
<concentrations>
<var name="N3n" value="1.739964749" ></var>
<var name="N1p" value="0.05973986885" ></var>
<var name="DIC" value="36.44620222" ></var>
<var name="POC" value="1.516579034" ></var>
<var name="DOC" value="2.290015211" ></var>
<var name="ALK" value="2.915344542" ></var>
</concentrations>
<Mouths><mouth I="680" J="261" id="37" name="Shkumbini"></mouth></Mouths>
</river>


<river name="Kopru" salinity="15.0" >
<concentrations>
<var name="N3n" value="2.059751119" ></var>
<var name="N1p" value="0.08267781733" ></var>
<var name="DIC" value="32.23431597" ></var>
<var name="POC" value="0" ></var>
<var name="DOC" value="0" ></var>
<var name="ALK" value="2.517943763" ></var>
</concentrations>
<Mouths><mouth I="962" J="160" id="46" name="Kopru"></mouth></Mouths>
</river>


<river name="Manavgat" salinity="15.0" >
<concentrations>
<var name="N3n" value="2.059751119" ></var>
<var name="N1p" value="0.08267781733" ></var>
<var name="DIC" value="32.23431597" ></var>
<var name="POC" value="0" ></var>
<var name="DOC" value="0" ></var>
<var name="ALK" value="2.517943763" ></var>
</concentrations>
<Mouths><mouth I="969" J="158" id="47" name="Manavgat"></mouth></Mouths>
</river>

<river name="Seyhan" salinity="15.0" >
<concentrations>
<var name="N3n" value="2.059751119" ></var>
<var name="N1p" value="0.08267781733" ></var>
<var name="DIC" value="32.23431597" ></var>
<var name="POC" value="0" ></var>
<var name="DOC" value="0" ></var>
<var name="ALK" value="2.517943763" ></var>
</concentrations>
<Mouths><mouth I="1051" J="158" id="48" name="Seyhan"></mouth></Mouths>
</river>


<river name="Ceyhan" salinity="15.0" >
<concentrations>
<var name="N3n" value="2.059751119" ></var>
<var name="N1p" value="0.08267781733" ></var>
<var name="DIC" value="32.23431597" ></var>
<var name="POC" value="0" ></var>
<var name="DOC" value="0" ></var>
<var name="ALK" value="2.517943763" ></var>
</concentrations>
<Mouths><mouth I="1067" J="154" id="49" name="Ceyhan"></mouth></Mouths>
</river>


<river name="Gosku" salinity="15.0" >
<concentrations>
<var name="N3n" value="2.059751119" ></var>
<var name="N1p" value="0.08267781733" ></var>
<var name="DIC" value="32.23431597" ></var>
<var name="POC" value="0" ></var>
<var name="DOC" value="0" ></var>
<var name="ALK" value="2.517943763" ></var>
</concentrations>
<Mouths><mouth I="1031" J="147" id="50" name="Gosku"></mouth></Mouths>
</river>



<river name="Asi/Orontes" salinity="15.0" >
<concentrations>
<var name="N3n" value="2.059751119" ></var>
<var name="N1p" value="0.08267781733" ></var>
<var name="DIC" value="32.23431597" ></var>
<var name="POC" value="0" ></var>
<var name="DOC" value="0" ></var>
<var name="ALK" value="2.517943763" ></var>
</concentrations>
<Mouths><mouth I="1076" J="142" id="52" name="Asi/Orontes"></mouth></Mouths>
</river>


<river name="Arno" salinity="15.0" >
<concentrations>
<var name="N3n" value="2.228379672" ></var>
<var name="N1p" value="0.2833101354" ></var>
<var name="DIC" value="52.96372484" ></var>
<var name="POC" value="0" ></var>
<var name="DOC" value="3.238446841" ></var>
<var name="ALK" value="5.159381996" ></var>
</concentrations>
<Mouths><mouth I="460" J="325" id="29" name="Arno"></mouth></Mouths>
</river>

<river name="Tevere" salinity="15.0" >
<concentrations>
<var name="N3n" value="2.228379672" ></var>
<var name="N1p" value="0.2833101354" ></var>
<var name="DIC" value="52.96372484" ></var>
<var name="POC" value="0" ></var>
<var name="DOC" value="3.238446841" ></var>
<var name="ALK" value="5.159381996" ></var>
</concentrations>
<Mouths>
<mouth I="507" J="278" id="33" name="Tevere 1"></mouth>
<mouth I="507" J="279" id="34" name="Tevere 2"></mouth>
</Mouths>
</river>

<river name="Volturno" salinity="15.0" >
<concentrations>
<var name="N3n" value="2.228379672" ></var>
<var name="N1p" value="0.2833101354" ></var>
<var name="DIC" value="52.96372484" ></var>
<var name="POC" value="0" ></var>
<var name="DOC" value="3.238446841" ></var>
<var name="ALK" value="5.159381996" ></var>
</concentrations>
<Mouths><mouth I="547" J="261" id="36" name="Volturno"></mouth></Mouths>
</river>

<river name="Medjerda" salinity="15.0" >
<concentrations>
<var name="N3n" value="2.55943321" ></var>
<var name="N1p" value="0.1723111546" ></var>
<var name="DIC" value="57.81148076" ></var>
<var name="POC" value="0" ></var>
<var name="DOC" value="0" ></var>
<var name="ALK" value="5.734942379" ></var>
</concentrations>
<Mouths><mouth I="459" J="165" id="51" name="Medjerda"></mouth></Mouths>
</river>

<river name="Ebro" salinity="30.0" >
<concentrations>
<var name="N3n" value="1.610126606" ></var>
<var name="N1p" value="0.09559021676" ></var>
<var name="DIC" value="31.6711725" ></var>
<var name="POC" value="1.838684022" ></var>
<var name="DOC" value="1.720550111" ></var>
<var name="ALK" value="2.871296943" ></var>
</concentrations>
<Mouths><mouth I="236" J="254" id="3" name="Ebro"></mouth></Mouths>
</river>

<river name="Rhone" salinity="25.0" >
<concentrations>
<var name="N3n" value="1.610126606" ></var>
<var name="N1p" value="0.09559021676" ></var>
<var name="DIC" value="31.6711725" ></var>
<var name="POC" value="1.838684022" ></var>
<var name="DOC" value="1.720550111" ></var>
<var name="ALK" value="2.871296943" ></var>
</concentrations>
<Mouths>
<mouth I="330" J="316" id="14" name="Grand Rhone"></mouth>
<mouth I="319" J="319" id="15" name="Petit Rhone"></mouth>
</Mouths>
</river>

<river name="Aude" salinity="15.0" >
<concentrations>
<var name="N3n" value="1.610126606" ></var>
<var name="N1p" value="0.09559021676" ></var>
<var name="DIC" value="31.6711725" ></var>
<var name="POC" value="1.838684022" ></var>
<var name="DOC" value="1.720550111" ></var>
<var name="ALK" value="2.871296943" ></var>
</concentrations>
<Mouths><mouth I="292" J="313" id="31" name="Aude"></mouth></Mouths>
</river>

<river name="Struma/Strymonas" salinity="15.0" >
<concentrations>
<var name="N3n" value="1.707923052" ></var>
<var name="N1p" value="0.3790870035" ></var>
<var name="DIC" value="34.40558202" ></var>
<var name="POC" value="0" ></var>
<var name="DOC" value="0" ></var>
<var name="ALK" value="2.617214852" ></var>
</concentrations>
<Mouths><mouth I="786" J="255" id="38" name="Struma/Strymonas"></mouth></Mouths>
</river>


<river name="Meric/Evros/Maritsa" salinity="15.0" >
<concentrations>
<var name="N3n" value="1.707923052" ></var>
<var name="N1p" value="0.3790870035" ></var>
<var name="DIC" value="34.40558202" ></var>
<var name="POC" value="0" ></var>
<var name="DOC" value="0" ></var>
<var name="ALK" value="2.617214852" ></var>
</concentrations>
<Mouths><mouth I="838" J="254" id="39" name="Meric/Evros/Maritsa"></mouth></Mouths>
</river>


<river name="Axios/Vadar" salinity="15.0" >
<concentrations>
<var name="N3n" value="1.707923052" ></var>
<var name="N1p" value="0.3790870035" ></var>
<var name="DIC" value="34.40558202" ></var>
<var name="POC" value="0" ></var>
<var name="DOC" value="0" ></var>
<var name="ALK" value="2.617214852" ></var>
</concentrations>
<Mouths><mouth I="759" J="248" id="40" name="Axios/Vadar"></mouth></Mouths>
</river>


<river name="Pinios" salinity="15.0" >
<concentrations>
<var name="N3n" value="1.707923052" ></var>
<var name="N1p" value="0.3790870035" ></var>
<var name="DIC" value="34.40558202" ></var>
<var name="POC" value="0" ></var>
<var name="DOC" value="0" ></var>
<var name="ALK" value="2.617214852" ></var>
</concentrations>
<Mouths><mouth I="760" J="235" id="42" name="Pinios"></mouth></Mouths>
</river>


<river name="Gediz" salinity="15.0" >
<concentrations>
<var name="N3n" value="1.707923052" ></var>
<var name="N1p" value="0.3790870035" ></var>
<var name="DIC" value="34.40558202" ></var>
<var name="POC" value="0" ></var>
<var name="DOC" value="0" ></var>
<var name="ALK" value="2.617214852" ></var>
</concentrations>
<Mouths><mouth I="856" J="203" id="44" name="Gediz"></mouth></Mouths>
</river>

<river name="Buyuk Menderes" salinity="15.0" >
<concentrations>
<var name="N3n" value="1.707923052" ></var>
<var name="N1p" value="0.3790870035" ></var>
<var name="DIC" value="34.40558202" ></var>
<var name="POC" value="0" ></var>
<var name="DOC" value="0" ></var>
<var name="ALK" value="2.617214852" ></var>
</concentrations>
<Mouths><mouth I="866" J="177" id="45" name="Buyuk Menderes"></mouth></Mouths>
</river>


<river name="Nile" salinity="8.0" >
<concentrations>
<var name="N3n" value="1.6101" ></var>
<var name="N1p" value="0.2714529606" ></var>
<var name="DIC" value="35.33372945" ></var>
<var name="POC" value="0" ></var>
<var name="DOC" value="0" ></var>
<var name="ALK" value="2.414895666" ></var>
</concentrations>
<Mouths>
<mouth I="943" J="33" id="1" name="Nile1"></mouth>
<mouth I="978" J="34" id="2" name="Nile2"></mouth>
</Mouths>
</river>


</RIVERS>

</root>
